LICENSE
MANIFEST.in
README
setup.py
Nib.egg-info/PKG-INFO
Nib.egg-info/SOURCES.txt
Nib.egg-info/dependency_links.txt
Nib.egg-info/requires.txt
Nib.egg-info/top_level.txt
bin/nib
nib/__init__.py
nib/build.py
nib/config.py
nib/defaults.nib
nib/document.py
nib/processor.py
nib/render.py
nib/resource.py
nib/sample.zip
nib/yaml.py
nib/plugins/__init__.py
nib/plugins/blog.py
nib/plugins/breadcrumbs.py
nib/plugins/indexpages.py
nib/plugins/lesscss.py
nib/plugins/markdown.py
nib/plugins/pages.py
nib/plugins/pagination.py
nib/plugins/prettyurls.py
nib/plugins/sass.py
nib/plugins/smartypants.py
nib/plugins/time.py