Metadata-Version: 1.1
Name: Nib
Version: 0.5.7
Summary: Static Site Generator
Home-page: https://github.com/jreese/nib
Author: John Reese
Author-email: john@noswap.com
License: MIT License
Platform: UNKNOWN
Classifier: License :: OSI Approved :: MIT License
Classifier: Operating System :: OS Independent
Classifier: Programming Language :: Python
Classifier: Programming Language :: Python :: 2.7
Classifier: Programming Language :: Python :: 3
Classifier: Programming Language :: Python :: 3.2
Classifier: Programming Language :: Python :: 3.3
Classifier: Topic :: Utilities
Classifier: Development Status :: 4 - Beta
Requires: sh (>=1.0)
Requires: Jinja2 (>=2.6)
Requires: Markdown (>=2.2.0)
Requires: PyYAML (>=3.10)
